{
    "disableAutoUpdate": false,
    "name": "BalderaMap",
    "author": "Hail . Snug",
    "description": "An electron GUI recreation of the Baldera area minimap.",
    "version": "(DEPRECATED) 1.0.3",
    "donationUrl": "https://play.google.com/store/apps/details?id=com.CarvedGames.SD",
    "options": {
        "guiName": "Baldera Map",
        "niceName": "BM",
        "settingsVersion": 1,
        "settingsFile": "config.json",
        "settingsMigrator": "config_generator.js"
    },
    "servers": ["https://raw.githubusercontent.com/hailstorming/Baldera-Map/main/"]
}